{
	"Type": "Generic",
	"GUID": "7A06CCE44822665F0A0EA9A2DC507F44",
	"Name": "Defense Counter",
	"CollisionType": "Penetrable",
	"Friction": 0.7,
	"Restitution": 0.3,
	"Density": 1,
	"SurfaceType": "Plastic",
	"Roughness": 0.4,
	"Metallic": 1,
	"PrimaryColor":
	{
		"R": 246,
		"G": 246,
		"B": 246
	},
	"SecondaryColor":
	{
		"R": 20,
		"G": 20,
		"B": 20
	},
	"Flippable": false,
	"Models": [
		{
			"Model": "Defense Counter.obj",
			"Offset":
			{
				"X": 0,
				"Y": 0,
				"Z": 0
			},
			"Scale":
			{
				"X": 1,
				"Y": 1,
				"Z": 1
			},
			"Rotation":
			{
				"X": 0,
				"Y": 0,
				"Z": 0
			},
			"IsTransparent": false,
			"UseOverrides": true,
			"SurfaceType": "Plastic"
		}
	],
	"Collision": [],
	"SnapPoints": []
}